sriparna/__init__.py
sriparna/apps.json
sriparna/sriparna.py
sriparna/sriparna_gui.py
termux_sriparna-1.0.4.dist-info/LICENSE
termux_sriparna-1.0.4.dist-info/METADATA
termux_sriparna-1.0.4.dist-info/WHEEL
termux_sriparna-1.0.4.dist-info/entry_points.txt
termux_sriparna-1.0.4.dist-info/top_level.txt
termux_sriparna-1.0.4.dist-info/RECORD
