Metadata-Version: 2.1
Name: termux-sriparna
Version: 1.0.4
Summary: A voice assistant for Termux written in python using Termux Api
Home-page: https://github.com/ayusc/termux-sriparna
Author: Ayus Chatterjee
Project-URL: Source Code, https://github.com/ayusc/termux-sriparna
Project-URL: Bug Tracker, https://github.com/ayusc/termux-sriparna/issues
Project-URL: Feature Requests, https://github.com/ayusc/termux-sriparna/issues/1
Keywords: python,voice assistant,termux,termux-api,g4f
License-File: LICENSE
